pop_inv/CartPolar.py
pop_inv/Legendre.py
pop_inv/POP.py
pop_inv/Projection.py
pop_inv/Quadrant.py
pop_inv/RBFs512.pkl
pop_inv/__init__.py
pop_inv/img.pkl
pop_inv-0.3.0.dist-info/licenses/LICENSE
pop_inv-0.3.0.dist-info/METADATA
pop_inv-0.3.0.dist-info/WHEEL
pop_inv-0.3.0.dist-info/top_level.txt
pop_inv-0.3.0.dist-info/RECORD
