Metadata-Version: 2.4
Name: pop_inv
Version: 0.3.0
Summary: Polar onion peeling for inverting VMI data
Author: Xligt
License: MIT
Project-URL: Homepage, https://github.com/xligt/pop
Keywords: polar,onion,peeling,VMI,inversion
Classifier: Programming Language :: Python :: 3
Classifier: License :: OSI Approved :: MIT License
Classifier: Operating System :: OS Independent
Requires-Python: >=3.8
License-File: LICENSE
Requires-Dist: numpy>=1.17
Requires-Dist: scipy>=1.5
Requires-Dist: scikit-learn>=0.24
Dynamic: license-file
